human_abi/__init__.py
human_abi-0.1.1.dist-info/LICENSE
human_abi-0.1.1.dist-info/METADATA
human_abi-0.1.1.dist-info/WHEEL
human_abi-0.1.1.dist-info/RECORD
